[
  {
    "id": "cpu-1",
    "name": "i7-8700K",
    "brand": "Intel",
    "price": 55000,
    "image": "https://placehold.co/200x200/525252/FFF?text=i7-8700K",
    "series": "Core/Pentium/Celeron",
    "generation": "8th Gen (Coffee Lake)",
    "cores": 6,
    "threads": 12,
    "usecase": "Flagship creator + high-FPS gaming",
    "generation_label": "8th Gen (Coffee Lake)",
    "stock": 100
  },
  {
    "id": "cpu-2",
    "name": "i7-8700",
    "brand": "Intel",
    "price": 35000,
    "image": "https://placehold.co/200x200/525252/FFF?text=i7-8700",
    "series": "Core/Pentium/Celeron",
    "generation": "8th Gen (Coffee Lake)",
    "cores": 6,
    "threads": 12,
    "usecase": "General purpose",
    "generation_label": "8th Gen (Coffee Lake)",
    "stock": 100
  },
  {
    "id": "cpu-3",
    "name": "i7-8700T",
    "brand": "Intel",
    "price": 35000,
    "image": "https://placehold.co/200x200/525252/FFF?text=i7-8700T",
    "series": "Core/Pentium/Celeron",
    "generation": "8th Gen (Coffee Lake)",
    "cores": 6,
    "threads": 12,
    "usecase": "General purpose",
    "generation_label": "8th Gen (Coffee Lake)",
    "stock": 100
  },
  {
    "id": "cpu-4",
    "name": "i7-8086K",
    "brand": "Intel",
    "price": 24000,
    "image": "https://placehold.co/200x200/525252/FFF?text=i7-8086K",
    "series": "Core/Pentium/Celeron",
    "generation": "8th Gen (Coffee Lake)",
    "cores": 6,
    "threads": 12,
    "usecase": "General purpose",
    "generation_label": "8th Gen (Coffee Lake)",
    "stock": 100
  },
  {
    "id": "cpu-5",
    "name": "i5-8600K",
    "brand": "Intel",
    "price": 30000,
    "image": "https://placehold.co/200x200/525252/FFF?text=i5-8600K",
    "series": "Core/Pentium/Celeron",
    "generation": "8th Gen (Coffee Lake)",
    "cores": 6,
    "threads": 6,
    "usecase": "Gaming + content creation",
    "generation_label": "8th Gen (Coffee Lake)",
    "stock": 100
  },
  {
    "id": "cpu-6",
    "name": "i5-8600",
    "brand": "Intel",
    "price": 22000,
    "image": "https://placehold.co/200x200/525252/FFF?text=i5-8600",
    "series": "Core/Pentium/Celeron",
    "generation": "8th Gen (Coffee Lake)",
    "cores": 6,
    "threads": 6,
    "usecase": "All-round (gaming + dev + creator lite)",
    "generation_label": "8th Gen (Coffee Lake)",
    "stock": 100
  },
  {
    "id": "cpu-7",
    "name": "i5-8600T",
    "brand": "Intel",
    "price": 22000,
    "image": "https://placehold.co/200x200/525252/FFF?text=i5-8600T",
    "series": "Core/Pentium/Celeron",
    "generation": "8th Gen (Coffee Lake)",
    "cores": 6,
    "threads": 6,
    "usecase": "All-round (gaming + dev + creator lite)",
    "generation_label": "8th Gen (Coffee Lake)",
    "stock": 100
  },
  {
    "id": "cpu-8",
    "name": "i5-8500",
    "brand": "Intel",
    "price": 22000,
    "image": "https://placehold.co/200x200/525252/FFF?text=i5-8500",
    "series": "Core/Pentium/Celeron",
    "generation": "8th Gen (Coffee Lake)",
    "cores": 6,
    "threads": 6,
    "usecase": "All-round (gaming + dev + creator lite)",
    "generation_label": "8th Gen (Coffee Lake)",
    "stock": 100
  },
  {
    "id": "cpu-9",
    "name": "i5-8500T",
    "brand": "Intel",
    "price": 22000,
    "image": "https://placehold.co/200x200/525252/FFF?text=i5-8500T",
    "series": "Core/Pentium/Celeron",
    "generation": "8th Gen (Coffee Lake)",
    "cores": 6,
    "threads": 6,
    "usecase": "All-round (gaming + dev + creator lite)",
    "generation_label": "8th Gen (Coffee Lake)",
    "stock": 100
  },
  {
    "id": "cpu-10",
    "name": "i5-8400",
    "brand": "Intel",
    "price": 22000,
    "image": "https://placehold.co/200x200/525252/FFF?text=i5-8400",
    "series": "Core/Pentium/Celeron",
    "generation": "8th Gen (Coffee Lake)",
    "cores": 6,
    "threads": 6,
    "usecase": "All-round (gaming + dev + creator lite)",
    "generation_label": "8th Gen (Coffee Lake)",
    "stock": 100
  },
  {
    "id": "cpu-11",
    "name": "i5-8400T",
    "brand": "Intel",
    "price": 22000,
    "image": "https://placehold.co/200x200/525252/FFF?text=i5-8400T",
    "series": "Core/Pentium/Celeron",
    "generation": "8th Gen (Coffee Lake)",
    "cores": 6,
    "threads": 6,
    "usecase": "All-round (gaming + dev + creator lite)",
    "generation_label": "8th Gen (Coffee Lake)",
    "stock": 100
  },
  {
    "id": "cpu-12",
    "name": "i3-8350K",
    "brand": "Intel",
    "price": 16000,
    "image": "https://placehold.co/200x200/525252/FFF?text=i3-8350K",
    "series": "Core/Pentium/Celeron",
    "generation": "8th Gen (Coffee Lake)",
    "cores": 4,
    "threads": 4,
    "usecase": "Budget build / office / dev",
    "generation_label": "8th Gen (Coffee Lake)",
    "stock": 100
  },
  {
    "id": "cpu-13",
    "name": "i3-8300",
    "brand": "Intel",
    "price": 14000,
    "image": "https://placehold.co/200x200/525252/FFF?text=i3-8300",
    "series": "Core/Pentium/Celeron",
    "generation": "8th Gen (Coffee Lake)",
    "cores": 4,
    "threads": 4,
    "usecase": "Budget build / office / dev",
    "generation_label": "8th Gen (Coffee Lake)",
    "stock": 100
  },
  {
    "id": "cpu-14",
    "name": "i3-8300T",
    "brand": "Intel",
    "price": 14000,
    "image": "https://placehold.co/200x200/525252/FFF?text=i3-8300T",
    "series": "Core/Pentium/Celeron",
    "generation": "8th Gen (Coffee Lake)",
    "cores": 4,
    "threads": 4,
    "usecase": "Budget build / office / dev",
    "generation_label": "8th Gen (Coffee Lake)",
    "stock": 100
  },
  {
    "id": "cpu-15",
    "name": "i3-8100",
    "brand": "Intel",
    "price": 14000,
    "image": "https://placehold.co/200x200/525252/FFF?text=i3-8100",
    "series": "Core/Pentium/Celeron",
    "generation": "8th Gen (Coffee Lake)",
    "cores": 4,
    "threads": 4,
    "usecase": "Budget build / office / dev",
    "generation_label": "8th Gen (Coffee Lake)",
    "stock": 100
  },
  {
    "id": "cpu-16",
    "name": "i3-8100T",
    "brand": "Intel",
    "price": 14000,
    "image": "https://placehold.co/200x200/525252/FFF?text=i3-8100T",
    "series": "Core/Pentium/Celeron",
    "generation": "8th Gen (Coffee Lake)",
    "cores": 4,
    "threads": 4,
    "usecase": "Budget build / office / dev",
    "generation_label": "8th Gen (Coffee Lake)",
    "stock": 100
  },
  {
    "id": "cpu-17",
    "name": "Pentium Gold G5600",
    "brand": "Intel",
    "price": 10000,
    "image": "https://placehold.co/200x200/525252/FFF?text=Pentium Gold G5600",
    "series": "Core/Pentium/Celeron",
    "generation": "8th Gen (Coffee Lake)",
    "cores": 2,
    "threads": 4,
    "usecase": "Basic/office/HTPC",
    "generation_label": "8th Gen (Coffee Lake)",
    "stock": 100
  },
  {
    "id": "cpu-18",
    "name": "Pentium Gold G5500",
    "brand": "Intel",
    "price": 10000,
    "image": "https://placehold.co/200x200/525252/FFF?text=Pentium Gold G5500",
    "series": "Core/Pentium/Celeron",
    "generation": "8th Gen (Coffee Lake)",
    "cores": 2,
    "threads": 4,
    "usecase": "Basic/office/HTPC",
    "generation_label": "8th Gen (Coffee Lake)",
    "stock": 100
  },
  {
    "id": "cpu-19",
    "name": "Pentium Gold G5400",
    "brand": "Intel",
    "price": 10000,
    "image": "https://placehold.co/200x200/525252/FFF?text=Pentium Gold G5400",
    "series": "Core/Pentium/Celeron",
    "generation": "8th Gen (Coffee Lake)",
    "cores": 2,
    "threads": 4,
    "usecase": "Basic/office/HTPC",
    "generation_label": "8th Gen (Coffee Lake)",
    "stock": 100
  },
  {
    "id": "cpu-20",
    "name": "Celeron G4920",
    "brand": "Intel",
    "price": 7000,
    "image": "https://placehold.co/200x200/525252/FFF?text=Celeron G4920",
    "series": "Core/Pentium/Celeron",
    "generation": "8th Gen (Coffee Lake)",
    "cores": 2,
    "threads": 2,
    "usecase": "Basic/office/HTPC",
    "generation_label": "8th Gen (Coffee Lake)",
    "stock": 100
  },
  {
    "id": "cpu-21",
    "name": "Celeron G4900",
    "brand": "Intel",
    "price": 7000,
    "image": "https://placehold.co/200x200/525252/FFF?text=Celeron G4900",
    "series": "Core/Pentium/Celeron",
    "generation": "8th Gen (Coffee Lake)",
    "cores": 2,
    "threads": 2,
    "usecase": "Basic/office/HTPC",
    "generation_label": "8th Gen (Coffee Lake)",
    "stock": 100
  },
  {
    "id": "cpu-22",
    "name": "i9-9900KS",
    "brand": "Intel",
    "price": 55000,
    "image": "https://placehold.co/200x200/525252/FFF?text=i9-9900KS",
    "series": "Core/Pentium/Celeron",
    "generation": "9th Gen (Coffee Lake-R)",
    "cores": 8,
    "threads": 16,
    "usecase": "Flagship creator + high-FPS gaming",
    "generation_label": "9th Gen (Coffee Lake-R)",
    "stock": 100
  },
  {
    "id": "cpu-23",
    "name": "i9-9900K",
    "brand": "Intel",
    "price": 55000,
    "image": "https://placehold.co/200x200/525252/FFF?text=i9-9900K",
    "series": "Core/Pentium/Celeron",
    "generation": "9th Gen (Coffee Lake-R)",
    "cores": 8,
    "threads": 16,
    "usecase": "Flagship creator + high-FPS gaming",
    "generation_label": "9th Gen (Coffee Lake-R)",
    "stock": 100
  },
  {
    "id": "cpu-24",
    "name": "i9-9900KF",
    "brand": "Intel",
    "price": 55000,
    "image": "https://placehold.co/200x200/525252/FFF?text=i9-9900KF",
    "series": "Core/Pentium/Celeron",
    "generation": "9th Gen (Coffee Lake-R)",
    "cores": 8,
    "threads": 16,
    "usecase": "Flagship creator + high-FPS gaming",
    "generation_label": "9th Gen (Coffee Lake-R)",
    "stock": 100
  },
  {
    "id": "cpu-25",
    "name": "i9-9900",
    "brand": "Intel",
    "price": 35000,
    "image": "https://placehold.co/200x200/525252/FFF?text=i9-9900",
    "series": "Core/Pentium/Celeron",
    "generation": "9th Gen (Coffee Lake-R)",
    "cores": 8,
    "threads": 16,
    "usecase": "General purpose",
    "generation_label": "9th Gen (Coffee Lake-R)",
    "stock": 100
  },
  {
    "id": "cpu-26",
    "name": "i9-9900F",
    "brand": "Intel",
    "price": 35000,
    "image": "https://placehold.co/200x200/525252/FFF?text=i9-9900F",
    "series": "Core/Pentium/Celeron",
    "generation": "9th Gen (Coffee Lake-R)",
    "cores": 8,
    "threads": 16,
    "usecase": "General purpose",
    "generation_label": "9th Gen (Coffee Lake-R)",
    "stock": 100
  },
  {
    "id": "cpu-27",
    "name": "i9-9900T",
    "brand": "Intel",
    "price": 35000,
    "image": "https://placehold.co/200x200/525252/FFF?text=i9-9900T",
    "series": "Core/Pentium/Celeron",
    "generation": "9th Gen (Coffee Lake-R)",
    "cores": 8,
    "threads": 16,
    "usecase": "General purpose",
    "generation_label": "9th Gen (Coffee Lake-R)",
    "stock": 100
  },
  {
    "id": "cpu-28",
    "name": "i7-9700K",
    "brand": "Intel",
    "price": 40000,
    "image": "https://placehold.co/200x200/525252/FFF?text=i7-9700K",
    "series": "Core/Pentium/Celeron",
    "generation": "9th Gen (Coffee Lake-R)",
    "cores": 8,
    "threads": 8,
    "usecase": "Gaming + content creation",
    "generation_label": "9th Gen (Coffee Lake-R)",
    "stock": 100
  },
  {
    "id": "cpu-29",
    "name": "i7-9700KF",
    "brand": "Intel",
    "price": 40000,
    "image": "https://placehold.co/200x200/525252/FFF?text=i7-9700KF",
    "series": "Core/Pentium/Celeron",
    "generation": "9th Gen (Coffee Lake-R)",
    "cores": 8,
    "threads": 8,
    "usecase": "Gaming + content creation",
    "generation_label": "9th Gen (Coffee Lake-R)",
    "stock": 100
  },
  {
    "id": "cpu-30",
    "name": "i7-9700",
    "brand": "Intel",
    "price": 35000,
    "image": "https://placehold.co/200x200/525252/FFF?text=i7-9700",
    "series": "Core/Pentium/Celeron",
    "generation": "9th Gen (Coffee Lake-R)",
    "cores": 8,
    "threads": 8,
    "usecase": "General purpose",
    "generation_label": "9th Gen (Coffee Lake-R)",
    "stock": 100
  },
  {
    "id": "cpu-31",
    "name": "i7-9700F",
    "brand": "Intel",
    "price": 35000,
    "image": "https://placehold.co/200x200/525252/FFF?text=i7-9700F",
    "series": "Core/Pentium/Celeron",
    "generation": "9th Gen (Coffee Lake-R)",
    "cores": 8,
    "threads": 8,
    "usecase": "General purpose",
    "generation_label": "9th Gen (Coffee Lake-R)",
    "stock": 100
  },
  {
    "id": "cpu-32",
    "name": "i5-9600K",
    "brand": "Intel",
    "price": 30000,
    "image": "https://placehold.co/200x200/525252/FFF?text=i5-9600K",
    "series": "Core/Pentium/Celeron",
    "generation": "9th Gen (Coffee Lake-R)",
    "cores": 6,
    "threads": 6,
    "usecase": "Gaming + content creation",
    "generation_label": "9th Gen (Coffee Lake-R)",
    "stock": 100
  },
  {
    "id": "cpu-33",
    "name": "i5-9600KF",
    "brand": "Intel",
    "price": 30000,
    "image": "https://placehold.co/200x200/525252/FFF?text=i5-9600KF",
    "series": "Core/Pentium/Celeron",
    "generation": "9th Gen (Coffee Lake-R)",
    "cores": 6,
    "threads": 6,
    "usecase": "Gaming + content creation",
    "generation_label": "9th Gen (Coffee Lake-R)",
    "stock": 100
  },
  {
    "id": "cpu-34",
    "name": "i5-9600",
    "brand": "Intel",
    "price": 22000,
    "image": "https://placehold.co/200x200/525252/FFF?text=i5-9600",
    "series": "Core/Pentium/Celeron",
    "generation": "9th Gen (Coffee Lake-R)",
    "cores": 6,
    "threads": 6,
    "usecase": "All-round (gaming + dev + creator lite)",
    "generation_label": "9th Gen (Coffee Lake-R)",
    "stock": 100
  },
  {
    "id": "cpu-35",
    "name": "i5-9500",
    "brand": "Intel",
    "price": 22000,
    "image": "https://placehold.co/200x200/525252/FFF?text=i5-9500",
    "series": "Core/Pentium/Celeron",
    "generation": "9th Gen (Coffee Lake-R)",
    "cores": 6,
    "threads": 6,
    "usecase": "All-round (gaming + dev + creator lite)",
    "generation_label": "9th Gen (Coffee Lake-R)",
    "stock": 100
  },
  {
    "id": "cpu-36",
    "name": "i5-9500F",
    "brand": "Intel",
    "price": 22000,
    "image": "https://placehold.co/200x200/525252/FFF?text=i5-9500F",
    "series": "Core/Pentium/Celeron",
    "generation": "9th Gen (Coffee Lake-R)",
    "cores": 6,
    "threads": 6,
    "usecase": "All-round (gaming + dev + creator lite)",
    "generation_label": "9th Gen (Coffee Lake-R)",
    "stock": 100
  },
  {
    "id": "cpu-37",
    "name": "i5-9400",
    "brand": "Intel",
    "price": 22000,
    "image": "https://placehold.co/200x200/525252/FFF?text=i5-9400",
    "series": "Core/Pentium/Celeron",
    "generation": "9th Gen (Coffee Lake-R)",
    "cores": 6,
    "threads": 6,
    "usecase": "All-round (gaming + dev + creator lite)",
    "generation_label": "9th Gen (Coffee Lake-R)",
    "stock": 100
  },
  {
    "id": "cpu-38",
    "name": "i5-9400F",
    "brand": "Intel",
    "price": 22000,
    "image": "https://placehold.co/200x200/525252/FFF?text=i5-9400F",
    "series": "Core/Pentium/Celeron",
    "generation": "9th Gen (Coffee Lake-R)",
    "cores": 6,
    "threads": 6,
    "usecase": "All-round (gaming + dev + creator lite)",
    "generation_label": "9th Gen (Coffee Lake-R)",
    "stock": 100
  },
  {
    "id": "cpu-39",
    "name": "i3-9350K",
    "brand": "Intel",
    "price": 16000,
    "image": "https://placehold.co/200x200/525252/FFF?text=i3-9350K",
    "series": "Core/Pentium/Celeron",
    "generation": "9th Gen (Coffee Lake-R)",
    "cores": 4,
    "threads": 4,
    "usecase": "Budget build / office / dev",
    "generation_label": "9th Gen (Coffee Lake-R)",
    "stock": 100
  },
  {
    "id": "cpu-40",
    "name": "i3-9300",
    "brand": "Intel",
    "price": 14000,
    "image": "https://placehold.co/200x200/525252/FFF?text=i3-9300",
    "series": "Core/Pentium/Celeron",
    "generation": "9th Gen (Coffee Lake-R)",
    "cores": 4,
    "threads": 4,
    "usecase": "Budget build / office / dev",
    "generation_label": "9th Gen (Coffee Lake-R)",
    "stock": 100
  },
  {
    "id": "cpu-41",
    "name": "i3-9100",
    "brand": "Intel",
    "price": 14000,
    "image": "https://placehold.co/200x200/525252/FFF?text=i3-9100",
    "series": "Core/Pentium/Celeron",
    "generation": "9th Gen (Coffee Lake-R)",
    "cores": 4,
    "threads": 4,
    "usecase": "Budget build / office / dev",
    "generation_label": "9th Gen (Coffee Lake-R)",
    "stock": 100
  },
  {
    "id": "cpu-42",
    "name": "i3-9100F",
    "brand": "Intel",
    "price": 14000,
    "image": "https://placehold.co/200x200/525252/FFF?text=i3-9100F",
    "series": "Core/Pentium/Celeron",
    "generation": "9th Gen (Coffee Lake-R)",
    "cores": 4,
    "threads": 4,
    "usecase": "Budget build / office / dev",
    "generation_label": "9th Gen (Coffee Lake-R)",
    "stock": 100
  },
  {
    "id": "cpu-43",
    "name": "Pentium Gold G5620",
    "brand": "Intel",
    "price": 10000,
    "image": "https://placehold.co/200x200/525252/FFF?text=Pentium Gold G5620",
    "series": "Core/Pentium/Celeron",
    "generation": "9th Gen (Coffee Lake-R)",
    "cores": 2,
    "threads": 4,
    "usecase": "Basic/office/HTPC",
    "generation_label": "9th Gen (Coffee Lake-R)",
    "stock": 100
  },
  {
    "id": "cpu-44",
    "name": "Pentium Gold G5600F",
    "brand": "Intel",
    "price": 10000,
    "image": "https://placehold.co/200x200/525252/FFF?text=Pentium Gold G5600F",
    "series": "Core/Pentium/Celeron",
    "generation": "9th Gen (Coffee Lake-R)",
    "cores": 2,
    "threads": 4,
    "usecase": "Basic/office/HTPC",
    "generation_label": "9th Gen (Coffee Lake-R)",
    "stock": 100
  },
  {
    "id": "cpu-45",
    "name": "Pentium Gold G5420",
    "brand": "Intel",
    "price": 10000,
    "image": "https://placehold.co/200x200/525252/FFF?text=Pentium Gold G5420",
    "series": "Core/Pentium/Celeron",
    "generation": "9th Gen (Coffee Lake-R)",
    "cores": 2,
    "threads": 4,
    "usecase": "Basic/office/HTPC",
    "generation_label": "9th Gen (Coffee Lake-R)",
    "stock": 100
  },
  {
    "id": "cpu-46",
    "name": "Celeron G4950",
    "brand": "Intel",
    "price": 7000,
    "image": "https://placehold.co/200x200/525252/FFF?text=Celeron G4950",
    "series": "Core/Pentium/Celeron",
    "generation": "9th Gen (Coffee Lake-R)",
    "cores": 2,
    "threads": 2,
    "usecase": "Basic/office/HTPC",
    "generation_label": "9th Gen (Coffee Lake-R)",
    "stock": 100
  },
  {
    "id": "cpu-47",
    "name": "Celeron G4930",
    "brand": "Intel",
    "price": 7000,
    "image": "https://placehold.co/200x200/525252/FFF?text=Celeron G4930",
    "series": "Core/Pentium/Celeron",
    "generation": "9th Gen (Coffee Lake-R)",
    "cores": 2,
    "threads": 2,
    "usecase": "Basic/office/HTPC",
    "generation_label": "9th Gen (Coffee Lake-R)",
    "stock": 100
  },
  {
    "id": "cpu-48",
    "name": "i9-10900K",
    "brand": "Intel",
    "price": 55000,
    "image": "https://placehold.co/200x200/525252/FFF?text=i9-10900K",
    "series": "Core/Pentium/Celeron",
    "generation": "10th Gen (Comet Lake)",
    "cores": 10,
    "threads": 20,
    "usecase": "Flagship creator + high-FPS gaming",
    "generation_label": "10th Gen (Comet Lake)",
    "stock": 100
  },
  {
    "id": "cpu-49",
    "name": "i9-10900KF",
    "brand": "Intel",
    "price": 55000,
    "image": "https://placehold.co/200x200/525252/FFF?text=i9-10900KF",
    "series": "Core/Pentium/Celeron",
    "generation": "10th Gen (Comet Lake)",
    "cores": 10,
    "threads": 20,
    "usecase": "Flagship creator + high-FPS gaming",
    "generation_label": "10th Gen (Comet Lake)",
    "stock": 100
  },
  {
    "id": "cpu-50",
    "name": "i9-10900",
    "brand": "Intel",
    "price": 35000,
    "image": "https://placehold.co/200x200/525252/FFF?text=i9-10900",
    "series": "Core/Pentium/Celeron",
    "generation": "10th Gen (Comet Lake)",
    "cores": 10,
    "threads": 20,
    "usecase": "General purpose",
    "generation_label": "10th Gen (Comet Lake)",
    "stock": 100
  },
  {
    "id": "cpu-51",
    "name": "i9-10900F",
    "brand": "Intel",
    "price": 35000,
    "image": "https://placehold.co/200x200/525252/FFF?text=i9-10900F",
    "series": "Core/Pentium/Celeron",
    "generation": "10th Gen (Comet Lake)",
    "cores": 10,
    "threads": 20,
    "usecase": "General purpose",
    "generation_label": "10th Gen (Comet Lake)",
    "stock": 100
  },
  {
    "id": "cpu-52",
    "name": "i9-10850K",
    "brand": "Intel",
    "price": 35000,
    "image": "https://placehold.co/200x200/525252/FFF?text=i9-10850K",
    "series": "Core/Pentium/Celeron",
    "generation": "10th Gen (Comet Lake)",
    "cores": 10,
    "threads": 20,
    "usecase": "General purpose",
    "generation_label": "10th Gen (Comet Lake)",
    "stock": 100
  },
  {
    "id": "cpu-53",
    "name": "i7-10700K",
    "brand": "Intel",
    "price": 40000,
    "image": "https://placehold.co/200x200/525252/FFF?text=i7-10700K",
    "series": "Core/Pentium/Celeron",
    "generation": "10th Gen (Comet Lake)",
    "cores": 8,
    "threads": 16,
    "usecase": "Gaming + content creation",
    "generation_label": "10th Gen (Comet Lake)",
    "stock": 100
  },
  {
    "id": "cpu-54",
    "name": "i7-10700KF",
    "brand": "Intel",
    "price": 40000,
    "image": "https://placehold.co/200x200/525252/FFF?text=i7-10700KF",
    "series": "Core/Pentium/Celeron",
    "generation": "10th Gen (Comet Lake)",
    "cores": 8,
    "threads": 16,
    "usecase": "Gaming + content creation",
    "generation_label": "10th Gen (Comet Lake)",
    "stock": 100
  },
  {
    "id": "cpu-55",
    "name": "i7-10700",
    "brand": "Intel",
    "price": 35000,
    "image": "https://placehold.co/200x200/525252/FFF?text=i7-10700",
    "series": "Core/Pentium/Celeron",
    "generation": "10th Gen (Comet Lake)",
    "cores": 8,
    "threads": 16,
    "usecase": "General purpose",
    "generation_label": "10th Gen (Comet Lake)",
    "stock": 100
  },
  {
    "id": "cpu-56",
    "name": "i7-10700F",
    "brand": "Intel",
    "price": 35000,
    "image": "https://placehold.co/200x200/525252/FFF?text=i7-10700F",
    "series": "Core/Pentium/Celeron",
    "generation": "10th Gen (Comet Lake)",
    "cores": 8,
    "threads": 16,
    "usecase": "General purpose",
    "generation_label": "10th Gen (Comet Lake)",
    "stock": 100
  },
  {
    "id": "cpu-57",
    "name": "i5-10600K",
    "brand": "Intel",
    "price": 30000,
    "image": "https://placehold.co/200x200/525252/FFF?text=i5-10600K",
    "series": "Core/Pentium/Celeron",
    "generation": "10th Gen (Comet Lake)",
    "cores": 6,
    "threads": 12,
    "usecase": "Gaming + content creation",
    "generation_label": "10th Gen (Comet Lake)",
    "stock": 100
  },
  {
    "id": "cpu-58",
    "name": "i5-10600KF",
    "brand": "Intel",
    "price": 30000,
    "image": "https://placehold.co/200x200/525252/FFF?text=i5-10600KF",
    "series": "Core/Pentium/Celeron",
    "generation": "10th Gen (Comet Lake)",
    "cores": 6,
    "threads": 12,
    "usecase": "Gaming + content creation",
    "generation_label": "10th Gen (Comet Lake)",
    "stock": 100
  },
  {
    "id": "cpu-59",
    "name": "i5-10600",
    "brand": "Intel",
    "price": 22000,
    "image": "https://placehold.co/200x200/525252/FFF?text=i5-10600",
    "series": "Core/Pentium/Celeron",
    "generation": "10th Gen (Comet Lake)",
    "cores": 6,
    "threads": 12,
    "usecase": "All-round (gaming + dev + creator lite)",
    "generation_label": "10th Gen (Comet Lake)",
    "stock": 100
  },
  {
    "id": "cpu-60",
    "name": "i5-10500",
    "brand": "Intel",
    "price": 22000,
    "image": "https://placehold.co/200x200/525252/FFF?text=i5-10500",
    "series": "Core/Pentium/Celeron",
    "generation": "10th Gen (Comet Lake)",
    "cores": 6,
    "threads": 12,
    "usecase": "All-round (gaming + dev + creator lite)",
    "generation_label": "10th Gen (Comet Lake)",
    "stock": 100
  },
  {
    "id": "cpu-61",
    "name": "i5-10400",
    "brand": "Intel",
    "price": 22000,
    "image": "https://placehold.co/200x200/525252/FFF?text=i5-10400",
    "series": "Core/Pentium/Celeron",
    "generation": "10th Gen (Comet Lake)",
    "cores": 6,
    "threads": 12,
    "usecase": "All-round (gaming + dev + creator lite)",
    "generation_label": "10th Gen (Comet Lake)",
    "stock": 100
  },
  {
    "id": "cpu-62",
    "name": "i5-10400F",
    "brand": "Intel",
    "price": 22000,
    "image": "https://placehold.co/200x200/525252/FFF?text=i5-10400F",
    "series": "Core/Pentium/Celeron",
    "generation": "10th Gen (Comet Lake)",
    "cores": 6,
    "threads": 12,
    "usecase": "All-round (gaming + dev + creator lite)",
    "generation_label": "10th Gen (Comet Lake)",
    "stock": 100
  },
  {
    "id": "cpu-63",
    "name": "i3-10320",
    "brand": "Intel",
    "price": 14000,
    "image": "https://placehold.co/200x200/525252/FFF?text=i3-10320",
    "series": "Core/Pentium/Celeron",
    "generation": "10th Gen (Comet Lake)",
    "cores": 4,
    "threads": 8,
    "usecase": "Budget build / office / dev",
    "generation_label": "10th Gen (Comet Lake)",
    "stock": 100
  },
  {
    "id": "cpu-64",
    "name": "i3-10300",
    "brand": "Intel",
    "price": 14000,
    "image": "https://placehold.co/200x200/525252/FFF?text=i3-10300",
    "series": "Core/Pentium/Celeron",
    "generation": "10th Gen (Comet Lake)",
    "cores": 4,
    "threads": 8,
    "usecase": "Budget build / office / dev",
    "generation_label": "10th Gen (Comet Lake)",
    "stock": 100
  },
  {
    "id": "cpu-65",
    "name": "i3-10100",
    "brand": "Intel",
    "price": 14000,
    "image": "https://placehold.co/200x200/525252/FFF?text=i3-10100",
    "series": "Core/Pentium/Celeron",
    "generation": "10th Gen (Comet Lake)",
    "cores": 4,
    "threads": 8,
    "usecase": "Budget build / office / dev",
    "generation_label": "10th Gen (Comet Lake)",
    "stock": 100
  },
  {
    "id": "cpu-66",
    "name": "i3-10100F",
    "brand": "Intel",
    "price": 14000,
    "image": "https://placehold.co/200x200/525252/FFF?text=i3-10100F",
    "series": "Core/Pentium/Celeron",
    "generation": "10th Gen (Comet Lake)",
    "cores": 4,
    "threads": 8,
    "usecase": "Budget build / office / dev",
    "generation_label": "10th Gen (Comet Lake)",
    "stock": 100
  },
  {
    "id": "cpu-67",
    "name": "Pentium Gold G6600",
    "brand": "Intel",
    "price": 10000,
    "image": "https://placehold.co/200x200/525252/FFF?text=Pentium Gold G6600",
    "series": "Core/Pentium/Celeron",
    "generation": "10th Gen (Comet Lake)",
    "cores": 2,
    "threads": 4,
    "usecase": "Basic/office/HTPC",
    "generation_label": "10th Gen (Comet Lake)",
    "stock": 100
  },
  {
    "id": "cpu-68",
    "name": "Pentium Gold G6500",
    "brand": "Intel",
    "price": 10000,
    "image": "https://placehold.co/200x200/525252/FFF?text=Pentium Gold G6500",
    "series": "Core/Pentium/Celeron",
    "generation": "10th Gen (Comet Lake)",
    "cores": 2,
    "threads": 4,
    "usecase": "Basic/office/HTPC",
    "generation_label": "10th Gen (Comet Lake)",
    "stock": 100
  },
  {
    "id": "cpu-69",
    "name": "Pentium Gold G6400",
    "brand": "Intel",
    "price": 10000,
    "image": "https://placehold.co/200x200/525252/FFF?text=Pentium Gold G6400",
    "series": "Core/Pentium/Celeron",
    "generation": "10th Gen (Comet Lake)",
    "cores": 2,
    "threads": 4,
    "usecase": "Basic/office/HTPC",
    "generation_label": "10th Gen (Comet Lake)",
    "stock": 100
  },
  {
    "id": "cpu-70",
    "name": "Celeron G5920",
    "brand": "Intel",
    "price": 7000,
    "image": "https://placehold.co/200x200/525252/FFF?text=Celeron G5920",
    "series": "Core/Pentium/Celeron",
    "generation": "10th Gen (Comet Lake)",
    "cores": 2,
    "threads": 2,
    "usecase": "Basic/office/HTPC",
    "generation_label": "10th Gen (Comet Lake)",
    "stock": 100
  },
  {
    "id": "cpu-71",
    "name": "Celeron G5900",
    "brand": "Intel",
    "price": 7000,
    "image": "https://placehold.co/200x200/525252/FFF?text=Celeron G5900",
    "series": "Core/Pentium/Celeron",
    "generation": "10th Gen (Comet Lake)",
    "cores": 2,
    "threads": 2,
    "usecase": "Basic/office/HTPC",
    "generation_label": "10th Gen (Comet Lake)",
    "stock": 100
  },
  {
    "id": "cpu-72",
    "name": "i9-10900T",
    "brand": "Intel",
    "price": 35000,
    "image": "https://placehold.co/200x200/525252/FFF?text=i9-10900T",
    "series": "Core/Pentium/Celeron",
    "generation": "10th Gen (Comet Lake)",
    "cores": 10,
    "threads": 20,
    "usecase": "General purpose",
    "generation_label": "10th Gen (Comet Lake)",
    "stock": 100
  },
  {
    "id": "cpu-73",
    "name": "i7-10700T",
    "brand": "Intel",
    "price": 35000,
    "image": "https://placehold.co/200x200/525252/FFF?text=i7-10700T",
    "series": "Core/Pentium/Celeron",
    "generation": "10th Gen (Comet Lake)",
    "cores": 8,
    "threads": 16,
    "usecase": "General purpose",
    "generation_label": "10th Gen (Comet Lake)",
    "stock": 100
  },
  {
    "id": "cpu-74",
    "name": "i5-10400T",
    "brand": "Intel",
    "price": 22000,
    "image": "https://placehold.co/200x200/525252/FFF?text=i5-10400T",
    "series": "Core/Pentium/Celeron",
    "generation": "10th Gen (Comet Lake)",
    "cores": 6,
    "threads": 12,
    "usecase": "All-round (gaming + dev + creator lite)",
    "generation_label": "10th Gen (Comet Lake)",
    "stock": 100
  },
  {
    "id": "cpu-75",
    "name": "i3-10100T",
    "brand": "Intel",
    "price": 14000,
    "image": "https://placehold.co/200x200/525252/FFF?text=i3-10100T",
    "series": "Core/Pentium/Celeron",
    "generation": "10th Gen (Comet Lake)",
    "cores": 4,
    "threads": 8,
    "usecase": "Budget build / office / dev",
    "generation_label": "10th Gen (Comet Lake)",
    "stock": 100
  },
  {
    "id": "cpu-76",
    "name": "i9-11900K",
    "brand": "Intel",
    "price": 55000,
    "image": "https://placehold.co/200x200/525252/FFF?text=i9-11900K",
    "series": "Core",
    "generation": "11th Gen (Rocket Lake)",
    "cores": 8,
    "threads": 16,
    "usecase": "Flagship creator + high-FPS gaming",
    "generation_label": "11th Gen (Rocket Lake)",
    "stock": 100
  },
  {
    "id": "cpu-77",
    "name": "i9-11900KF",
    "brand": "Intel",
    "price": 55000,
    "image": "https://placehold.co/200x200/525252/FFF?text=i9-11900KF",
    "series": "Core",
    "generation": "11th Gen (Rocket Lake)",
    "cores": 8,
    "threads": 16,
    "usecase": "Flagship creator + high-FPS gaming",
    "generation_label": "11th Gen (Rocket Lake)",
    "stock": 100
  },
  {
    "id": "cpu-78",
    "name": "i9-11900",
    "brand": "Intel",
    "price": 35000,
    "image": "https://placehold.co/200x200/525252/FFF?text=i9-11900",
    "series": "Core",
    "generation": "11th Gen (Rocket Lake)",
    "cores": 8,
    "threads": 16,
    "usecase": "General purpose",
    "generation_label": "11th Gen (Rocket Lake)",
    "stock": 100
  },
  {
    "id": "cpu-79",
    "name": "i9-11900F",
    "brand": "Intel",
    "price": 35000,
    "image": "https://placehold.co/200x200/525252/FFF?text=i9-11900F",
    "series": "Core",
    "generation": "11th Gen (Rocket Lake)",
    "cores": 8,
    "threads": 16,
    "usecase": "General purpose",
    "generation_label": "11th Gen (Rocket Lake)",
    "stock": 100
  },
  {
    "id": "cpu-80",
    "name": "i7-11700K",
    "brand": "Intel",
    "price": 40000,
    "image": "https://placehold.co/200x200/525252/FFF?text=i7-11700K",
    "series": "Core",
    "generation": "11th Gen (Rocket Lake)",
    "cores": 8,
    "threads": 16,
    "usecase": "Gaming + content creation",
    "generation_label": "11th Gen (Rocket Lake)",
    "stock": 100
  },
  {
    "id": "cpu-81",
    "name": "i7-11700KF",
    "brand": "Intel",
    "price": 40000,
    "image": "https://placehold.co/200x200/525252/FFF?text=i7-11700KF",
    "series": "Core",
    "generation": "11th Gen (Rocket Lake)",
    "cores": 8,
    "threads": 16,
    "usecase": "Gaming + content creation",
    "generation_label": "11th Gen (Rocket Lake)",
    "stock": 100
  },
  {
    "id": "cpu-82",
    "name": "i7-11700",
    "brand": "Intel",
    "price": 35000,
    "image": "https://placehold.co/200x200/525252/FFF?text=i7-11700",
    "series": "Core",
    "generation": "11th Gen (Rocket Lake)",
    "cores": 8,
    "threads": 16,
    "usecase": "General purpose",
    "generation_label": "11th Gen (Rocket Lake)",
    "stock": 100
  },
  {
    "id": "cpu-83",
    "name": "i7-11700F",
    "brand": "Intel",
    "price": 35000,
    "image": "https://placehold.co/200x200/525252/FFF?text=i7-11700F",
    "series": "Core",
    "generation": "11th Gen (Rocket Lake)",
    "cores": 8,
    "threads": 16,
    "usecase": "General purpose",
    "generation_label": "11th Gen (Rocket Lake)",
    "stock": 100
  },
  {
    "id": "cpu-84",
    "name": "i5-11600K",
    "brand": "Intel",
    "price": 30000,
    "image": "https://placehold.co/200x200/525252/FFF?text=i5-11600K",
    "series": "Core",
    "generation": "11th Gen (Rocket Lake)",
    "cores": 6,
    "threads": 12,
    "usecase": "Gaming + content creation",
    "generation_label": "11th Gen (Rocket Lake)",
    "stock": 100
  },
  {
    "id": "cpu-85",
    "name": "i5-11600KF",
    "brand": "Intel",
    "price": 30000,
    "image": "https://placehold.co/200x200/525252/FFF?text=i5-11600KF",
    "series": "Core",
    "generation": "11th Gen (Rocket Lake)",
    "cores": 6,
    "threads": 12,
    "usecase": "Gaming + content creation",
    "generation_label": "11th Gen (Rocket Lake)",
    "stock": 100
  },
  {
    "id": "cpu-86",
    "name": "i5-11600",
    "brand": "Intel",
    "price": 22000,
    "image": "https://placehold.co/200x200/525252/FFF?text=i5-11600",
    "series": "Core",
    "generation": "11th Gen (Rocket Lake)",
    "cores": 6,
    "threads": 12,
    "usecase": "All-round (gaming + dev + creator lite)",
    "generation_label": "11th Gen (Rocket Lake)",
    "stock": 100
  },
  {
    "id": "cpu-87",
    "name": "i5-11500",
    "brand": "Intel",
    "price": 22000,
    "image": "https://placehold.co/200x200/525252/FFF?text=i5-11500",
    "series": "Core",
    "generation": "11th Gen (Rocket Lake)",
    "cores": 6,
    "threads": 12,
    "usecase": "All-round (gaming + dev + creator lite)",
    "generation_label": "11th Gen (Rocket Lake)",
    "stock": 100
  },
  {
    "id": "cpu-88",
    "name": "i5-11400",
    "brand": "Intel",
    "price": 22000,
    "image": "https://placehold.co/200x200/525252/FFF?text=i5-11400",
    "series": "Core",
    "generation": "11th Gen (Rocket Lake)",
    "cores": 6,
    "threads": 12,
    "usecase": "All-round (gaming + dev + creator lite)",
    "generation_label": "11th Gen (Rocket Lake)",
    "stock": 100
  },
  {
    "id": "cpu-89",
    "name": "i5-11400F",
    "brand": "Intel",
    "price": 22000,
    "image": "https://placehold.co/200x200/525252/FFF?text=i5-11400F",
    "series": "Core",
    "generation": "11th Gen (Rocket Lake)",
    "cores": 6,
    "threads": 12,
    "usecase": "All-round (gaming + dev + creator lite)",
    "generation_label": "11th Gen (Rocket Lake)",
    "stock": 100
  },
  {
    "id": "cpu-90",
    "name": "i9-11900T",
    "brand": "Intel",
    "price": 35000,
    "image": "https://placehold.co/200x200/525252/FFF?text=i9-11900T",
    "series": "Core",
    "generation": "11th Gen (Rocket Lake)",
    "cores": 8,
    "threads": 16,
    "usecase": "General purpose",
    "generation_label": "11th Gen (Rocket Lake)",
    "stock": 100
  },
  {
    "id": "cpu-91",
    "name": "i7-11700T",
    "brand": "Intel",
    "price": 35000,
    "image": "https://placehold.co/200x200/525252/FFF?text=i7-11700T",
    "series": "Core",
    "generation": "11th Gen (Rocket Lake)",
    "cores": 8,
    "threads": 16,
    "usecase": "General purpose",
    "generation_label": "11th Gen (Rocket Lake)",
    "stock": 100
  },
  {
    "id": "cpu-92",
    "name": "i5-11400T",
    "brand": "Intel",
    "price": 22000,
    "image": "https://placehold.co/200x200/525252/FFF?text=i5-11400T",
    "series": "Core",
    "generation": "11th Gen (Rocket Lake)",
    "cores": 6,
    "threads": 12,
    "usecase": "All-round (gaming + dev + creator lite)",
    "generation_label": "11th Gen (Rocket Lake)",
    "stock": 100
  },
  {
    "id": "cpu-93",
    "name": "i9-12900KS",
    "brand": "Intel",
    "price": 55000,
    "image": "https://placehold.co/200x200/525252/FFF?text=i9-12900KS",
    "series": "Core/Pentium/Celeron",
    "generation": "12th Gen (Alder Lake)",
    "cores": 24,
    "threads": 32,
    "usecase": "Flagship creator + high-FPS gaming",
    "generation_label": "12th Gen (Alder Lake)",
    "stock": 100
  },
  {
    "id": "cpu-94",
    "name": "i9-12900K",
    "brand": "Intel",
    "price": 55000,
    "image": "https://placehold.co/200x200/525252/FFF?text=i9-12900K",
    "series": "Core/Pentium/Celeron",
    "generation": "12th Gen (Alder Lake)",
    "cores": 24,
    "threads": 32,
    "usecase": "Flagship creator + high-FPS gaming",
    "generation_label": "12th Gen (Alder Lake)",
    "stock": 100
  },
  {
    "id": "cpu-95",
    "name": "i9-12900KF",
    "brand": "Intel",
    "price": 55000,
    "image": "https://placehold.co/200x200/525252/FFF?text=i9-12900KF",
    "series": "Core/Pentium/Celeron",
    "generation": "12th Gen (Alder Lake)",
    "cores": 24,
    "threads": 32,
    "usecase": "Flagship creator + high-FPS gaming",
    "generation_label": "12th Gen (Alder Lake)",
    "stock": 100
  },
  {
    "id": "cpu-96",
    "name": "i9-12900",
    "brand": "Intel",
    "price": 35000,
    "image": "https://placehold.co/200x200/525252/FFF?text=i9-12900",
    "series": "Core/Pentium/Celeron",
    "generation": "12th Gen (Alder Lake)",
    "cores": 24,
    "threads": 32,
    "usecase": "General purpose",
    "generation_label": "12th Gen (Alder Lake)",
    "stock": 100
  },
  {
    "id": "cpu-97",
    "name": "i9-12900F",
    "brand": "Intel",
    "price": 35000,
    "image": "https://placehold.co/200x200/525252/FFF?text=i9-12900F",
    "series": "Core/Pentium/Celeron",
    "generation": "12th Gen (Alder Lake)",
    "cores": 24,
    "threads": 32,
    "usecase": "General purpose",
    "generation_label": "12th Gen (Alder Lake)",
    "stock": 100
  },
  {
    "id": "cpu-98",
    "name": "i7-12700K",
    "brand": "Intel",
    "price": 40000,
    "image": "https://placehold.co/200x200/525252/FFF?text=i7-12700K",
    "series": "Core/Pentium/Celeron",
    "generation": "12th Gen (Alder Lake)",
    "cores": 12,
    "threads": 20,
    "usecase": "Gaming + content creation",
    "generation_label": "12th Gen (Alder Lake)",
    "stock": 100
  },
  {
    "id": "cpu-99",
    "name": "i7-12700KF",
    "brand": "Intel",
    "price": 40000,
    "image": "https://placehold.co/200x200/525252/FFF?text=i7-12700KF",
    "series": "Core/Pentium/Celeron",
    "generation": "12th Gen (Alder Lake)",
    "cores": 12,
    "threads": 20,
    "usecase": "Gaming + content creation",
    "generation_label": "12th Gen (Alder Lake)",
    "stock": 100
  },
  {
    "id": "cpu-100",
    "name": "i7-12700",
    "brand": "Intel",
    "price": 35000,
    "image": "https://placehold.co/200x200/525252/FFF?text=i7-12700",
    "series": "Core/Pentium/Celeron",
    "generation": "12th Gen (Alder Lake)",
    "cores": 12,
    "threads": 20,
    "usecase": "General purpose",
    "generation_label": "12th Gen (Alder Lake)",
    "stock": 100
  },
  {
    "id": "cpu-101",
    "name": "i7-12700F",
    "brand": "Intel",
    "price": 35000,
    "image": "https://placehold.co/200x200/525252/FFF?text=i7-12700F",
    "series": "Core/Pentium/Celeron",
    "generation": "12th Gen (Alder Lake)",
    "cores": 12,
    "threads": 20,
    "usecase": "General purpose",
    "generation_label": "12th Gen (Alder Lake)",
    "stock": 100
  },
  {
    "id": "cpu-102",
    "name": "i5-12600K",
    "brand": "Intel",
    "price": 30000,
    "image": "https://placehold.co/200x200/525252/FFF?text=i5-12600K",
    "series": "Core/Pentium/Celeron",
    "generation": "12th Gen (Alder Lake)",
    "cores": 10,
    "threads": 16,
    "usecase": "Gaming + content creation",
    "generation_label": "12th Gen (Alder Lake)",
    "stock": 100
  },
  {
    "id": "cpu-103",
    "name": "i5-12600KF",
    "brand": "Intel",
    "price": 30000,
    "image": "https://placehold.co/200x200/525252/FFF?text=i5-12600KF",
    "series": "Core/Pentium/Celeron",
    "generation": "12th Gen (Alder Lake)",
    "cores": 10,
    "threads": 16,
    "usecase": "Gaming + content creation",
    "generation_label": "12th Gen (Alder Lake)",
    "stock": 100
  },
  {
    "id": "cpu-104",
    "name": "i5-12600",
    "brand": "Intel",
    "price": 22000,
    "image": "https://placehold.co/200x200/525252/FFF?text=i5-12600",
    "series": "Core/Pentium/Celeron",
    "generation": "12th Gen (Alder Lake)",
    "cores": 10,
    "threads": 16,
    "usecase": "All-round (gaming + dev + creator lite)",
    "generation_label": "12th Gen (Alder Lake)",
    "stock": 100
  },
  {
    "id": "cpu-105",
    "name": "i5-12500",
    "brand": "Intel",
    "price": 22000,
    "image": "https://placehold.co/200x200/525252/FFF?text=i5-12500",
    "series": "Core/Pentium/Celeron",
    "generation": "12th Gen (Alder Lake)",
    "cores": 6,
    "threads": 12,
    "usecase": "All-round (gaming + dev + creator lite)",
    "generation_label": "12th Gen (Alder Lake)",
    "stock": 100
  },
  {
    "id": "cpu-106",
    "name": "i5-12400",
    "brand": "Intel",
    "price": 22000,
    "image": "https://placehold.co/200x200/525252/FFF?text=i5-12400",
    "series": "Core/Pentium/Celeron",
    "generation": "12th Gen (Alder Lake)",
    "cores": 6,
    "threads": 12,
    "usecase": "All-round (gaming + dev + creator lite)",
    "generation_label": "12th Gen (Alder Lake)",
    "stock": 100
  },
  {
    "id": "cpu-107",
    "name": "i5-12400F",
    "brand": "Intel",
    "price": 22000,
    "image": "https://placehold.co/200x200/525252/FFF?text=i5-12400F",
    "series": "Core/Pentium/Celeron",
    "generation": "12th Gen (Alder Lake)",
    "cores": 6,
    "threads": 12,
    "usecase": "All-round (gaming + dev + creator lite)",
    "generation_label": "12th Gen (Alder Lake)",
    "stock": 100
  },
  {
    "id": "cpu-108",
    "name": "i3-12300",
    "brand": "Intel",
    "price": 14000,
    "image": "https://placehold.co/200x200/525252/FFF?text=i3-12300",
    "series": "Core/Pentium/Celeron",
    "generation": "12th Gen (Alder Lake)",
    "cores": 4,
    "threads": 8,
    "usecase": "Budget build / office / dev",
    "generation_label": "12th Gen (Alder Lake)",
    "stock": 100
  },
  {
    "id": "cpu-109",
    "name": "i3-12100",
    "brand": "Intel",
    "price": 14000,
    "image": "https://placehold.co/200x200/525252/FFF?text=i3-12100",
    "series": "Core/Pentium/Celeron",
    "generation": "12th Gen (Alder Lake)",
    "cores": 4,
    "threads": 8,
    "usecase": "Budget build / office / dev",
    "generation_label": "12th Gen (Alder Lake)",
    "stock": 100
  },
  {
    "id": "cpu-110",
    "name": "i3-12100F",
    "brand": "Intel",
    "price": 14000,
    "image": "https://placehold.co/200x200/525252/FFF?text=i3-12100F",
    "series": "Core/Pentium/Celeron",
    "generation": "12th Gen (Alder Lake)",
    "cores": 4,
    "threads": 8,
    "usecase": "Budget build / office / dev",
    "generation_label": "12th Gen (Alder Lake)",
    "stock": 100
  },
  {
    "id": "cpu-111",
    "name": "Pentium Gold G7400",
    "brand": "Intel",
    "price": 10000,
    "image": "https://placehold.co/200x200/525252/FFF?text=Pentium Gold G7400",
    "series": "Core/Pentium/Celeron",
    "generation": "12th Gen (Alder Lake)",
    "cores": 2,
    "threads": 4,
    "usecase": "Basic/office/HTPC",
    "generation_label": "12th Gen (Alder Lake)",
    "stock": 100
  },
  {
    "id": "cpu-112",
    "name": "Celeron G6900",
    "brand": "Intel",
    "price": 7000,
    "image": "https://placehold.co/200x200/525252/FFF?text=Celeron G6900",
    "series": "Core/Pentium/Celeron",
    "generation": "12th Gen (Alder Lake)",
    "cores": 2,
    "threads": 2,
    "usecase": "Basic/office/HTPC",
    "generation_label": "12th Gen (Alder Lake)",
    "stock": 100
  },
  {
    "id": "cpu-113",
    "name": "i9-12900T",
    "brand": "Intel",
    "price": 35000,
    "image": "https://placehold.co/200x200/525252/FFF?text=i9-12900T",
    "series": "Core/Pentium/Celeron",
    "generation": "12th Gen (Alder Lake)",
    "cores": 24,
    "threads": 32,
    "usecase": "General purpose",
    "generation_label": "12th Gen (Alder Lake)",
    "stock": 100
  },
  {
    "id": "cpu-114",
    "name": "i7-12700T",
    "brand": "Intel",
    "price": 35000,
    "image": "https://placehold.co/200x200/525252/FFF?text=i7-12700T",
    "series": "Core/Pentium/Celeron",
    "generation": "12th Gen (Alder Lake)",
    "cores": 12,
    "threads": 20,
    "usecase": "General purpose",
    "generation_label": "12th Gen (Alder Lake)",
    "stock": 100
  },
  {
    "id": "cpu-115",
    "name": "i5-12600T",
    "brand": "Intel",
    "price": 22000,
    "image": "https://placehold.co/200x200/525252/FFF?text=i5-12600T",
    "series": "Core/Pentium/Celeron",
    "generation": "12th Gen (Alder Lake)",
    "cores": 10,
    "threads": 16,
    "usecase": "All-round (gaming + dev + creator lite)",
    "generation_label": "12th Gen (Alder Lake)",
    "stock": 100
  },
  {
    "id": "cpu-116",
    "name": "i5-12400T",
    "brand": "Intel",
    "price": 22000,
    "image": "https://placehold.co/200x200/525252/FFF?text=i5-12400T",
    "series": "Core/Pentium/Celeron",
    "generation": "12th Gen (Alder Lake)",
    "cores": 6,
    "threads": 12,
    "usecase": "All-round (gaming + dev + creator lite)",
    "generation_label": "12th Gen (Alder Lake)",
    "stock": 100
  },
  {
    "id": "cpu-117",
    "name": "i3-12100T",
    "brand": "Intel",
    "price": 14000,
    "image": "https://placehold.co/200x200/525252/FFF?text=i3-12100T",
    "series": "Core/Pentium/Celeron",
    "generation": "12th Gen (Alder Lake)",
    "cores": 4,
    "threads": 8,
    "usecase": "Budget build / office / dev",
    "generation_label": "12th Gen (Alder Lake)",
    "stock": 100
  },
  {
    "id": "cpu-118",
    "name": "i9-13900KS",
    "brand": "Intel",
    "price": 55000,
    "image": "https://placehold.co/200x200/525252/FFF?text=i9-13900KS",
    "series": "Core",
    "generation": "13th Gen (Raptor Lake)",
    "cores": 24,
    "threads": 32,
    "usecase": "Flagship creator + high-FPS gaming",
    "generation_label": "13th Gen (Raptor Lake)",
    "stock": 100
  },
  {
    "id": "cpu-119",
    "name": "i9-13900K",
    "brand": "Intel",
    "price": 55000,
    "image": "https://placehold.co/200x200/525252/FFF?text=i9-13900K",
    "series": "Core",
    "generation": "13th Gen (Raptor Lake)",
    "cores": 24,
    "threads": 32,
    "usecase": "Flagship creator + high-FPS gaming",
    "generation_label": "13th Gen (Raptor Lake)",
    "stock": 100
  },
  {
    "id": "cpu-120",
    "name": "i9-13900KF",
    "brand": "Intel",
    "price": 55000,
    "image": "https://placehold.co/200x200/525252/FFF?text=i9-13900KF",
    "series": "Core",
    "generation": "13th Gen (Raptor Lake)",
    "cores": 24,
    "threads": 32,
    "usecase": "Flagship creator + high-FPS gaming",
    "generation_label": "13th Gen (Raptor Lake)",
    "stock": 100
  },
  {
    "id": "cpu-121",
    "name": "i9-13900",
    "brand": "Intel",
    "price": 35000,
    "image": "https://placehold.co/200x200/525252/FFF?text=i9-13900",
    "series": "Core",
    "generation": "13th Gen (Raptor Lake)",
    "cores": 24,
    "threads": 32,
    "usecase": "General purpose",
    "generation_label": "13th Gen (Raptor Lake)",
    "stock": 100
  },
  {
    "id": "cpu-122",
    "name": "i9-13900F",
    "brand": "Intel",
    "price": 35000,
    "image": "https://placehold.co/200x200/525252/FFF?text=i9-13900F",
    "series": "Core",
    "generation": "13th Gen (Raptor Lake)",
    "cores": 24,
    "threads": 32,
    "usecase": "General purpose",
    "generation_label": "13th Gen (Raptor Lake)",
    "stock": 100
  },
  {
    "id": "cpu-123",
    "name": "i7-13700K",
    "brand": "Intel",
    "price": 40000,
    "image": "https://placehold.co/200x200/525252/FFF?text=i7-13700K",
    "series": "Core",
    "generation": "13th Gen (Raptor Lake)",
    "cores": 16,
    "threads": 24,
    "usecase": "Gaming + content creation",
    "generation_label": "13th Gen (Raptor Lake)",
    "stock": 100
  },
  {
    "id": "cpu-124",
    "name": "i7-13700KF",
    "brand": "Intel",
    "price": 40000,
    "image": "https://placehold.co/200x200/525252/FFF?text=i7-13700KF",
    "series": "Core",
    "generation": "13th Gen (Raptor Lake)",
    "cores": 16,
    "threads": 24,
    "usecase": "Gaming + content creation",
    "generation_label": "13th Gen (Raptor Lake)",
    "stock": 100
  },
  {
    "id": "cpu-125",
    "name": "i7-13700",
    "brand": "Intel",
    "price": 35000,
    "image": "https://placehold.co/200x200/525252/FFF?text=i7-13700",
    "series": "Core",
    "generation": "13th Gen (Raptor Lake)",
    "cores": 16,
    "threads": 24,
    "usecase": "General purpose",
    "generation_label": "13th Gen (Raptor Lake)",
    "stock": 100
  },
  {
    "id": "cpu-126",
    "name": "i7-13700F",
    "brand": "Intel",
    "price": 35000,
    "image": "https://placehold.co/200x200/525252/FFF?text=i7-13700F",
    "series": "Core",
    "generation": "13th Gen (Raptor Lake)",
    "cores": 16,
    "threads": 24,
    "usecase": "General purpose",
    "generation_label": "13th Gen (Raptor Lake)",
    "stock": 100
  },
  {
    "id": "cpu-127",
    "name": "i5-13600K",
    "brand": "Intel",
    "price": 30000,
    "image": "https://placehold.co/200x200/525252/FFF?text=i5-13600K",
    "series": "Core",
    "generation": "13th Gen (Raptor Lake)",
    "cores": 14,
    "threads": 20,
    "usecase": "Gaming + content creation",
    "generation_label": "13th Gen (Raptor Lake)",
    "stock": 100
  },
  {
    "id": "cpu-128",
    "name": "i5-13600KF",
    "brand": "Intel",
    "price": 30000,
    "image": "https://placehold.co/200x200/525252/FFF?text=i5-13600KF",
    "series": "Core",
    "generation": "13th Gen (Raptor Lake)",
    "cores": 14,
    "threads": 20,
    "usecase": "Gaming + content creation",
    "generation_label": "13th Gen (Raptor Lake)",
    "stock": 100
  },
  {
    "id": "cpu-129",
    "name": "i5-13600",
    "brand": "Intel",
    "price": 22000,
    "image": "https://placehold.co/200x200/525252/FFF?text=i5-13600",
    "series": "Core",
    "generation": "13th Gen (Raptor Lake)",
    "cores": 14,
    "threads": 20,
    "usecase": "All-round (gaming + dev + creator lite)",
    "generation_label": "13th Gen (Raptor Lake)",
    "stock": 100
  },
  {
    "id": "cpu-130",
    "name": "i5-13500",
    "brand": "Intel",
    "price": 22000,
    "image": "https://placehold.co/200x200/525252/FFF?text=i5-13500",
    "series": "Core",
    "generation": "13th Gen (Raptor Lake)",
    "cores": 14,
    "threads": 20,
    "usecase": "All-round (gaming + dev + creator lite)",
    "generation_label": "13th Gen (Raptor Lake)",
    "stock": 100
  },
  {
    "id": "cpu-131",
    "name": "i5-13400",
    "brand": "Intel",
    "price": 22000,
    "image": "https://placehold.co/200x200/525252/FFF?text=i5-13400",
    "series": "Core",
    "generation": "13th Gen (Raptor Lake)",
    "cores": 10,
    "threads": 16,
    "usecase": "All-round (gaming + dev + creator lite)",
    "generation_label": "13th Gen (Raptor Lake)",
    "stock": 100
  },
  {
    "id": "cpu-132",
    "name": "i5-13400F",
    "brand": "Intel",
    "price": 22000,
    "image": "https://placehold.co/200x200/525252/FFF?text=i5-13400F",
    "series": "Core",
    "generation": "13th Gen (Raptor Lake)",
    "cores": 10,
    "threads": 16,
    "usecase": "All-round (gaming + dev + creator lite)",
    "generation_label": "13th Gen (Raptor Lake)",
    "stock": 100
  },
  {
    "id": "cpu-133",
    "name": "i3-13100",
    "brand": "Intel",
    "price": 14000,
    "image": "https://placehold.co/200x200/525252/FFF?text=i3-13100",
    "series": "Core",
    "generation": "13th Gen (Raptor Lake)",
    "cores": 4,
    "threads": 8,
    "usecase": "Budget build / office / dev",
    "generation_label": "13th Gen (Raptor Lake)",
    "stock": 100
  },
  {
    "id": "cpu-134",
    "name": "i3-13100F",
    "brand": "Intel",
    "price": 14000,
    "image": "https://placehold.co/200x200/525252/FFF?text=i3-13100F",
    "series": "Core",
    "generation": "13th Gen (Raptor Lake)",
    "cores": 4,
    "threads": 8,
    "usecase": "Budget build / office / dev",
    "generation_label": "13th Gen (Raptor Lake)",
    "stock": 100
  },
  {
    "id": "cpu-135",
    "name": "i9-13900T",
    "brand": "Intel",
    "price": 35000,
    "image": "https://placehold.co/200x200/525252/FFF?text=i9-13900T",
    "series": "Core",
    "generation": "13th Gen (Raptor Lake)",
    "cores": 24,
    "threads": 32,
    "usecase": "General purpose",
    "generation_label": "13th Gen (Raptor Lake)",
    "stock": 100
  },
  {
    "id": "cpu-136",
    "name": "i7-13700T",
    "brand": "Intel",
    "price": 35000,
    "image": "https://placehold.co/200x200/525252/FFF?text=i7-13700T",
    "series": "Core",
    "generation": "13th Gen (Raptor Lake)",
    "cores": 16,
    "threads": 24,
    "usecase": "General purpose",
    "generation_label": "13th Gen (Raptor Lake)",
    "stock": 100
  },
  {
    "id": "cpu-137",
    "name": "i5-13600T",
    "brand": "Intel",
    "price": 22000,
    "image": "https://placehold.co/200x200/525252/FFF?text=i5-13600T",
    "series": "Core",
    "generation": "13th Gen (Raptor Lake)",
    "cores": 14,
    "threads": 20,
    "usecase": "All-round (gaming + dev + creator lite)",
    "generation_label": "13th Gen (Raptor Lake)",
    "stock": 100
  },
  {
    "id": "cpu-138",
    "name": "i5-13500T",
    "brand": "Intel",
    "price": 22000,
    "image": "https://placehold.co/200x200/525252/FFF?text=i5-13500T",
    "series": "Core",
    "generation": "13th Gen (Raptor Lake)",
    "cores": 14,
    "threads": 20,
    "usecase": "All-round (gaming + dev + creator lite)",
    "generation_label": "13th Gen (Raptor Lake)",
    "stock": 100
  },
  {
    "id": "cpu-139",
    "name": "i5-13400T",
    "brand": "Intel",
    "price": 22000,
    "image": "https://placehold.co/200x200/525252/FFF?text=i5-13400T",
    "series": "Core",
    "generation": "13th Gen (Raptor Lake)",
    "cores": 10,
    "threads": 16,
    "usecase": "All-round (gaming + dev + creator lite)",
    "generation_label": "13th Gen (Raptor Lake)",
    "stock": 100
  },
  {
    "id": "cpu-140",
    "name": "i3-13100T",
    "brand": "Intel",
    "price": 14000,
    "image": "https://placehold.co/200x200/525252/FFF?text=i3-13100T",
    "series": "Core",
    "generation": "13th Gen (Raptor Lake)",
    "cores": 4,
    "threads": 8,
    "usecase": "Budget build / office / dev",
    "generation_label": "13th Gen (Raptor Lake)",
    "stock": 100
  },
  {
    "id": "cpu-141",
    "name": "Ryzen 7 1800X",
    "brand": "AMD",
    "price": 55000,
    "image": "https://placehold.co/200x200/525252/FFF?text=Ryzen 7 1800X",
    "series": "Ryzen",
    "generation": "1000 (Zen 1)",
    "cores": 8,
    "threads": 16,
    "usecase": "Flagship creator + high-FPS gaming",
    "generation_label": "1000 (Zen 1)",
    "stock": 100
  },
  {
    "id": "cpu-142",
    "name": "Ryzen 7 1700X",
    "brand": "AMD",
    "price": 35000,
    "image": "https://placehold.co/200x200/525252/FFF?text=Ryzen 7 1700X",
    "series": "Ryzen",
    "generation": "1000 (Zen 1)",
    "cores": 8,
    "threads": 16,
    "usecase": "General purpose",
    "generation_label": "1000 (Zen 1)",
    "stock": 100
  },
  {
    "id": "cpu-143",
    "name": "Ryzen 7 1700",
    "brand": "AMD",
    "price": 35000,
    "image": "https://placehold.co/200x200/525252/FFF?text=Ryzen 7 1700",
    "series": "Ryzen",
    "generation": "1000 (Zen 1)",
    "cores": 8,
    "threads": 16,
    "usecase": "General purpose",
    "generation_label": "1000 (Zen 1)",
    "stock": 100
  },
  {
    "id": "cpu-144",
    "name": "Ryzen 5 1600X",
    "brand": "AMD",
    "price": 30000,
    "image": "https://placehold.co/200x200/525252/FFF?text=Ryzen 5 1600X",
    "series": "Ryzen",
    "generation": "1000 (Zen 1)",
    "cores": 6,
    "threads": 12,
    "usecase": "Gaming + content creation",
    "generation_label": "1000 (Zen 1)",
    "stock": 100
  },
  {
    "id": "cpu-145",
    "name": "Ryzen 5 1600",
    "brand": "AMD",
    "price": 22000,
    "image": "https://placehold.co/200x200/525252/FFF?text=Ryzen 5 1600",
    "series": "Ryzen",
    "generation": "1000 (Zen 1)",
    "cores": 6,
    "threads": 12,
    "usecase": "All-round (gaming + dev + creator lite)",
    "generation_label": "1000 (Zen 1)",
    "stock": 100
  },
  {
    "id": "cpu-146",
    "name": "Ryzen 5 1500X",
    "brand": "AMD",
    "price": 22000,
    "image": "https://placehold.co/200x200/525252/FFF?text=Ryzen 5 1500X",
    "series": "Ryzen",
    "generation": "1000 (Zen 1)",
    "cores": 4,
    "threads": 8,
    "usecase": "All-round (gaming + dev + creator lite)",
    "generation_label": "1000 (Zen 1)",
    "stock": 100
  },
  {
    "id": "cpu-147",
    "name": "Ryzen 3 1300X",
    "brand": "AMD",
    "price": 14000,
    "image": "https://placehold.co/200x200/525252/FFF?text=Ryzen 3 1300X",
    "series": "Ryzen",
    "generation": "1000 (Zen 1)",
    "cores": 4,
    "threads": 4,
    "usecase": "Budget build / office / dev",
    "generation_label": "1000 (Zen 1)",
    "stock": 100
  },
  {
    "id": "cpu-148",
    "name": "Ryzen 3 1200",
    "brand": "AMD",
    "price": 14000,
    "image": "https://placehold.co/200x200/525252/FFF?text=Ryzen 3 1200",
    "series": "Ryzen",
    "generation": "1000 (Zen 1)",
    "cores": 4,
    "threads": 4,
    "usecase": "Budget build / office / dev",
    "generation_label": "1000 (Zen 1)",
    "stock": 100
  },
  {
    "id": "cpu-149",
    "name": "Ryzen 5 1400",
    "brand": "AMD",
    "price": 14000,
    "image": "https://placehold.co/200x200/525252/FFF?text=Ryzen 5 1400",
    "series": "Ryzen",
    "generation": "1000 (Zen 1)",
    "cores": 4,
    "threads": 8,
    "usecase": "Budget build / office / dev",
    "generation_label": "1000 (Zen 1)",
    "stock": 100
  },
  {
    "id": "cpu-150",
    "name": "Ryzen 7 2700X",
    "brand": "AMD",
    "price": 55000,
    "image": "https://placehold.co/200x200/525252/FFF?text=Ryzen 7 2700X",
    "series": "Ryzen",
    "generation": "2000 (Zen+)",
    "cores": 8,
    "threads": 16,
    "usecase": "Flagship creator + high-FPS gaming",
    "generation_label": "2000 (Zen+)",
    "stock": 100
  },
  {
    "id": "cpu-151",
    "name": "Ryzen 7 2700",
    "brand": "AMD",
    "price": 35000,
    "image": "https://placehold.co/200x200/525252/FFF?text=Ryzen 7 2700",
    "series": "Ryzen",
    "generation": "2000 (Zen+)",
    "cores": 8,
    "threads": 16,
    "usecase": "General purpose",
    "generation_label": "2000 (Zen+)",
    "stock": 100
  },
  {
    "id": "cpu-152",
    "name": "Ryzen 5 2600X",
    "brand": "AMD",
    "price": 30000,
    "image": "https://placehold.co/200x200/525252/FFF?text=Ryzen 5 2600X",
    "series": "Ryzen",
    "generation": "2000 (Zen+)",
    "cores": 6,
    "threads": 12,
    "usecase": "Gaming + content creation",
    "generation_label": "2000 (Zen+)",
    "stock": 100
  },
  {
    "id": "cpu-153",
    "name": "Ryzen 5 2600",
    "brand": "AMD",
    "price": 22000,
    "image": "https://placehold.co/200x200/525252/FFF?text=Ryzen 5 2600",
    "series": "Ryzen",
    "generation": "2000 (Zen+)",
    "cores": 6,
    "threads": 12,
    "usecase": "All-round (gaming + dev + creator lite)",
    "generation_label": "2000 (Zen+)",
    "stock": 100
  },
  {
    "id": "cpu-154",
    "name": "Ryzen 5 2500X",
    "brand": "AMD",
    "price": 22000,
    "image": "https://placehold.co/200x200/525252/FFF?text=Ryzen 5 2500X",
    "series": "Ryzen",
    "generation": "2000 (Zen+)",
    "cores": 4,
    "threads": 8,
    "usecase": "All-round (gaming + dev + creator lite)",
    "generation_label": "2000 (Zen+)",
    "stock": 100
  },
  {
    "id": "cpu-155",
    "name": "Ryzen 5 2400G",
    "brand": "AMD",
    "price": 22000,
    "image": "https://placehold.co/200x200/525252/FFF?text=Ryzen 5 2400G",
    "series": "Ryzen",
    "generation": "2000 (Zen+)",
    "cores": 4,
    "threads": 8,
    "usecase": "All-round (gaming + dev + creator lite)",
    "generation_label": "2000 (Zen+)",
    "stock": 100
  },
  {
    "id": "cpu-156",
    "name": "Ryzen 3 2200G",
    "brand": "AMD",
    "price": 14000,
    "image": "https://placehold.co/200x200/525252/FFF?text=Ryzen 3 2200G",
    "series": "Ryzen",
    "generation": "2000 (Zen+)",
    "cores": 4,
    "threads": 4,
    "usecase": "Budget build / office / dev",
    "generation_label": "2000 (Zen+)",
    "stock": 100
  },
  {
    "id": "cpu-157",
    "name": "Ryzen 9 3950X",
    "brand": "AMD",
    "price": 55000,
    "image": "https://placehold.co/200x200/525252/FFF?text=Ryzen 9 3950X",
    "series": "Ryzen",
    "generation": "3000 (Zen 2)",
    "cores": 16,
    "threads": 32,
    "usecase": "Flagship creator + high-FPS gaming",
    "generation_label": "3000 (Zen 2)",
    "stock": 100
  },
  {
    "id": "cpu-158",
    "name": "Ryzen 9 3900XT",
    "brand": "AMD",
    "price": 35000,
    "image": "https://placehold.co/200x200/525252/FFF?text=Ryzen 9 3900XT",
    "series": "Ryzen",
    "generation": "3000 (Zen 2)",
    "cores": 12,
    "threads": 24,
    "usecase": "General purpose",
    "generation_label": "3000 (Zen 2)",
    "stock": 100
  },
  {
    "id": "cpu-159",
    "name": "Ryzen 9 3900X",
    "brand": "AMD",
    "price": 35000,
    "image": "https://placehold.co/200x200/525252/FFF?text=Ryzen 9 3900X",
    "series": "Ryzen",
    "generation": "3000 (Zen 2)",
    "cores": 12,
    "threads": 24,
    "usecase": "General purpose",
    "generation_label": "3000 (Zen 2)",
    "stock": 100
  },
  {
    "id": "cpu-160",
    "name": "Ryzen 7 3800XT",
    "brand": "AMD",
    "price": 40000,
    "image": "https://placehold.co/200x200/525252/FFF?text=Ryzen 7 3800XT",
    "series": "Ryzen",
    "generation": "3000 (Zen 2)",
    "cores": 8,
    "threads": 16,
    "usecase": "Gaming + content creation",
    "generation_label": "3000 (Zen 2)",
    "stock": 100
  },
  {
    "id": "cpu-161",
    "name": "Ryzen 7 3800X",
    "brand": "AMD",
    "price": 40000,
    "image": "https://placehold.co/200x200/525252/FFF?text=Ryzen 7 3800X",
    "series": "Ryzen",
    "generation": "3000 (Zen 2)",
    "cores": 8,
    "threads": 16,
    "usecase": "Gaming + content creation",
    "generation_label": "3000 (Zen 2)",
    "stock": 100
  },
  {
    "id": "cpu-162",
    "name": "Ryzen 7 3700X",
    "brand": "AMD",
    "price": 35000,
    "image": "https://placehold.co/200x200/525252/FFF?text=Ryzen 7 3700X",
    "series": "Ryzen",
    "generation": "3000 (Zen 2)",
    "cores": 8,
    "threads": 16,
    "usecase": "General purpose",
    "generation_label": "3000 (Zen 2)",
    "stock": 100
  },
  {
    "id": "cpu-163",
    "name": "Ryzen 5 3600XT",
    "brand": "AMD",
    "price": 30000,
    "image": "https://placehold.co/200x200/525252/FFF?text=Ryzen 5 3600XT",
    "series": "Ryzen",
    "generation": "3000 (Zen 2)",
    "cores": 6,
    "threads": 12,
    "usecase": "Gaming + content creation",
    "generation_label": "3000 (Zen 2)",
    "stock": 100
  },
  {
    "id": "cpu-164",
    "name": "Ryzen 5 3600X",
    "brand": "AMD",
    "price": 30000,
    "image": "https://placehold.co/200x200/525252/FFF?text=Ryzen 5 3600X",
    "series": "Ryzen",
    "generation": "3000 (Zen 2)",
    "cores": 6,
    "threads": 12,
    "usecase": "Gaming + content creation",
    "generation_label": "3000 (Zen 2)",
    "stock": 100
  },
  {
    "id": "cpu-165",
    "name": "Ryzen 5 3600",
    "brand": "AMD",
    "price": 22000,
    "image": "https://placehold.co/200x200/525252/FFF?text=Ryzen 5 3600",
    "series": "Ryzen",
    "generation": "3000 (Zen 2)",
    "cores": 6,
    "threads": 12,
    "usecase": "All-round (gaming + dev + creator lite)",
    "generation_label": "3000 (Zen 2)",
    "stock": 100
  },
  {
    "id": "cpu-166",
    "name": "Ryzen 3 3300X",
    "brand": "AMD",
    "price": 16000,
    "image": "https://placehold.co/200x200/525252/FFF?text=Ryzen 3 3300X",
    "series": "Ryzen",
    "generation": "3000 (Zen 2)",
    "cores": 4,
    "threads": 8,
    "usecase": "Budget build / office / dev",
    "generation_label": "3000 (Zen 2)",
    "stock": 100
  },
  {
    "id": "cpu-167",
    "name": "Ryzen 3 3100",
    "brand": "AMD",
    "price": 14000,
    "image": "https://placehold.co/200x200/525252/FFF?text=Ryzen 3 3100",
    "series": "Ryzen",
    "generation": "3000 (Zen 2)",
    "cores": 4,
    "threads": 8,
    "usecase": "Budget build / office / dev",
    "generation_label": "3000 (Zen 2)",
    "stock": 100
  },
  {
    "id": "cpu-168",
    "name": "Ryzen 5 3400G",
    "brand": "AMD",
    "price": 22000,
    "image": "https://placehold.co/200x200/525252/FFF?text=Ryzen 5 3400G",
    "series": "Ryzen",
    "generation": "3000 (Zen 2)",
    "cores": 4,
    "threads": 8,
    "usecase": "All-round (gaming + dev + creator lite)",
    "generation_label": "3000 (Zen 2)",
    "stock": 100
  },
  {
    "id": "cpu-169",
    "name": "Ryzen 3 3200G",
    "brand": "AMD",
    "price": 14000,
    "image": "https://placehold.co/200x200/525252/FFF?text=Ryzen 3 3200G",
    "series": "Ryzen",
    "generation": "3000 (Zen 2)",
    "cores": 4,
    "threads": 4,
    "usecase": "Budget build / office / dev",
    "generation_label": "3000 (Zen 2)",
    "stock": 100
  },
  {
    "id": "cpu-170",
    "name": "Ryzen 5 3500X",
    "brand": "AMD",
    "price": 22000,
    "image": "https://placehold.co/200x200/525252/FFF?text=Ryzen 5 3500X",
    "series": "Ryzen",
    "generation": "3000 (Zen 2)",
    "cores": 6,
    "threads": 6,
    "usecase": "All-round (gaming + dev + creator lite)",
    "generation_label": "3000 (Zen 2)",
    "stock": 100
  },
  {
    "id": "cpu-171",
    "name": "Ryzen 5 3500",
    "brand": "AMD",
    "price": 22000,
    "image": "https://placehold.co/200x200/525252/FFF?text=Ryzen 5 3500",
    "series": "Ryzen",
    "generation": "3000 (Zen 2)",
    "cores": 6,
    "threads": 6,
    "usecase": "All-round (gaming + dev + creator lite)",
    "generation_label": "3000 (Zen 2)",
    "stock": 100
  },
  {
    "id": "cpu-172",
    "name": "Ryzen 7 4700G",
    "brand": "AMD",
    "price": 35000,
    "image": "https://placehold.co/200x200/525252/FFF?text=Ryzen 7 4700G",
    "series": "Ryzen",
    "generation": "4000G (Zen 2 APU)",
    "cores": 8,
    "threads": 16,
    "usecase": "iGPU-only build / SFF",
    "generation_label": "4000G (Zen 2 APU)",
    "stock": 100
  },
  {
    "id": "cpu-173",
    "name": "Ryzen 5 4600G",
    "brand": "AMD",
    "price": 22000,
    "image": "https://placehold.co/200x200/525252/FFF?text=Ryzen 5 4600G",
    "series": "Ryzen",
    "generation": "4000G (Zen 2 APU)",
    "cores": 6,
    "threads": 12,
    "usecase": "All-round (gaming + dev + creator lite)",
    "generation_label": "4000G (Zen 2 APU)",
    "stock": 100
  },
  {
    "id": "cpu-174",
    "name": "Ryzen 3 4300G",
    "brand": "AMD",
    "price": 14000,
    "image": "https://placehold.co/200x200/525252/FFF?text=Ryzen 3 4300G",
    "series": "Ryzen",
    "generation": "4000G (Zen 2 APU)",
    "cores": 4,
    "threads": 8,
    "usecase": "Budget build / office / dev",
    "generation_label": "4000G (Zen 2 APU)",
    "stock": 100
  },
  {
    "id": "cpu-175",
    "name": "Ryzen 9 5950X",
    "brand": "AMD",
    "price": 55000,
    "image": "https://placehold.co/200x200/525252/FFF?text=Ryzen 9 5950X",
    "series": "Ryzen",
    "generation": "5000 (Zen 3)",
    "cores": 16,
    "threads": 32,
    "usecase": "Flagship creator + high-FPS gaming",
    "generation_label": "5000 (Zen 3)",
    "stock": 100
  },
  {
    "id": "cpu-176",
    "name": "Ryzen 9 5900X",
    "brand": "AMD",
    "price": 35000,
    "image": "https://placehold.co/200x200/525252/FFF?text=Ryzen 9 5900X",
    "series": "Ryzen",
    "generation": "5000 (Zen 3)",
    "cores": 12,
    "threads": 24,
    "usecase": "General purpose",
    "generation_label": "5000 (Zen 3)",
    "stock": 100
  },
  {
    "id": "cpu-177",
    "name": "Ryzen 9 5900",
    "brand": "AMD",
    "price": 35000,
    "image": "https://placehold.co/200x200/525252/FFF?text=Ryzen 9 5900",
    "series": "Ryzen",
    "generation": "5000 (Zen 3)",
    "cores": 12,
    "threads": 24,
    "usecase": "General purpose",
    "generation_label": "5000 (Zen 3)",
    "stock": 100
  },
  {
    "id": "cpu-178",
    "name": "Ryzen 7 5800X3D",
    "brand": "AMD",
    "price": 40000,
    "image": "https://placehold.co/200x200/525252/FFF?text=Ryzen 7 5800X3D",
    "series": "Ryzen",
    "generation": "5000 (Zen 3)",
    "cores": 8,
    "threads": 16,
    "usecase": "Gaming-first",
    "generation_label": "5000 (Zen 3)",
    "stock": 100
  },
  {
    "id": "cpu-179",
    "name": "Ryzen 7 5800X",
    "brand": "AMD",
    "price": 40000,
    "image": "https://placehold.co/200x200/525252/FFF?text=Ryzen 7 5800X",
    "series": "Ryzen",
    "generation": "5000 (Zen 3)",
    "cores": 8,
    "threads": 16,
    "usecase": "Gaming + content creation",
    "generation_label": "5000 (Zen 3)",
    "stock": 100
  },
  {
    "id": "cpu-180",
    "name": "Ryzen 7 5700X",
    "brand": "AMD",
    "price": 35000,
    "image": "https://placehold.co/200x200/525252/FFF?text=Ryzen 7 5700X",
    "series": "Ryzen",
    "generation": "5000 (Zen 3)",
    "cores": 8,
    "threads": 16,
    "usecase": "General purpose",
    "generation_label": "5000 (Zen 3)",
    "stock": 100
  },
  {
    "id": "cpu-181",
    "name": "Ryzen 7 5700",
    "brand": "AMD",
    "price": 35000,
    "image": "https://placehold.co/200x200/525252/FFF?text=Ryzen 7 5700",
    "series": "Ryzen",
    "generation": "5000 (Zen 3)",
    "cores": 8,
    "threads": 16,
    "usecase": "General purpose",
    "generation_label": "5000 (Zen 3)",
    "stock": 100
  },
  {
    "id": "cpu-182",
    "name": "Ryzen 5 5600X",
    "brand": "AMD",
    "price": 30000,
    "image": "https://placehold.co/200x200/525252/FFF?text=Ryzen 5 5600X",
    "series": "Ryzen",
    "generation": "5000 (Zen 3)",
    "cores": 6,
    "threads": 12,
    "usecase": "Gaming + content creation",
    "generation_label": "5000 (Zen 3)",
    "stock": 100
  },
  {
    "id": "cpu-183",
    "name": "Ryzen 5 5600",
    "brand": "AMD",
    "price": 22000,
    "image": "https://placehold.co/200x200/525252/FFF?text=Ryzen 5 5600",
    "series": "Ryzen",
    "generation": "5000 (Zen 3)",
    "cores": 6,
    "threads": 12,
    "usecase": "All-round (gaming + dev + creator lite)",
    "generation_label": "5000 (Zen 3)",
    "stock": 100
  },
  {
    "id": "cpu-184",
    "name": "Ryzen 5 5500",
    "brand": "AMD",
    "price": 22000,
    "image": "https://placehold.co/200x200/525252/FFF?text=Ryzen 5 5500",
    "series": "Ryzen",
    "generation": "5000 (Zen 3)",
    "cores": 6,
    "threads": 12,
    "usecase": "Budget build / office / dev",
    "generation_label": "5000 (Zen 3)",
    "stock": 100
  },
  {
    "id": "cpu-185",
    "name": "Ryzen 3 5300",
    "brand": "AMD",
    "price": 14000,
    "image": "https://placehold.co/200x200/525252/FFF?text=Ryzen 3 5300",
    "series": "Ryzen",
    "generation": "5000 (Zen 3)",
    "cores": 4,
    "threads": 8,
    "usecase": "Budget build / office / dev",
    "generation_label": "5000 (Zen 3)",
    "stock": 100
  },
  {
    "id": "cpu-186",
    "name": "Ryzen 7 5700G",
    "brand": "AMD",
    "price": 35000,
    "image": "https://placehold.co/200x200/525252/FFF?text=Ryzen 7 5700G",
    "series": "Ryzen",
    "generation": "5000 (Zen 3)",
    "cores": 8,
    "threads": 16,
    "usecase": "iGPU-only build / SFF",
    "generation_label": "5000 (Zen 3)",
    "stock": 100
  },
  {
    "id": "cpu-187",
    "name": "Ryzen 5 5600G",
    "brand": "AMD",
    "price": 22000,
    "image": "https://placehold.co/200x200/525252/FFF?text=Ryzen 5 5600G",
    "series": "Ryzen",
    "generation": "5000 (Zen 3)",
    "cores": 6,
    "threads": 12,
    "usecase": "All-round (gaming + dev + creator lite)",
    "generation_label": "5000 (Zen 3)",
    "stock": 100
  },
  {
    "id": "cpu-188",
    "name": "Ryzen 3 5300G",
    "brand": "AMD",
    "price": 14000,
    "image": "https://placehold.co/200x200/525252/FFF?text=Ryzen 3 5300G",
    "series": "Ryzen",
    "generation": "5000 (Zen 3)",
    "cores": 4,
    "threads": 8,
    "usecase": "Budget build / office / dev",
    "generation_label": "5000 (Zen 3)",
    "stock": 100
  },
  {
    "id": "cpu-189",
    "name": "Ryzen 9 7950X3D",
    "brand": "AMD",
    "price": 55000,
    "image": "https://placehold.co/200x200/525252/FFF?text=Ryzen 9 7950X3D",
    "series": "Ryzen",
    "generation": "7000 (Zen 4)",
    "cores": 16,
    "threads": 32,
    "usecase": "Elite gaming + creator",
    "generation_label": "7000 (Zen 4)",
    "stock": 100
  },
  {
    "id": "cpu-190",
    "name": "Ryzen 9 7950X",
    "brand": "AMD",
    "price": 55000,
    "image": "https://placehold.co/200x200/525252/FFF?text=Ryzen 9 7950X",
    "series": "Ryzen",
    "generation": "7000 (Zen 4)",
    "cores": 16,
    "threads": 32,
    "usecase": "Flagship creator + high-FPS gaming",
    "generation_label": "7000 (Zen 4)",
    "stock": 100
  },
  {
    "id": "cpu-191",
    "name": "Ryzen 9 7900X3D",
    "brand": "AMD",
    "price": 40000,
    "image": "https://placehold.co/200x200/525252/FFF?text=Ryzen 9 7900X3D",
    "series": "Ryzen",
    "generation": "7000 (Zen 4)",
    "cores": 12,
    "threads": 24,
    "usecase": "Gaming-first",
    "generation_label": "7000 (Zen 4)",
    "stock": 100
  },
  {
    "id": "cpu-192",
    "name": "Ryzen 9 7900X",
    "brand": "AMD",
    "price": 40000,
    "image": "https://placehold.co/200x200/525252/FFF?text=Ryzen 9 7900X",
    "series": "Ryzen",
    "generation": "7000 (Zen 4)",
    "cores": 12,
    "threads": 24,
    "usecase": "Gaming + content creation",
    "generation_label": "7000 (Zen 4)",
    "stock": 100
  },
  {
    "id": "cpu-193",
    "name": "Ryzen 9 7900",
    "brand": "AMD",
    "price": 35000,
    "image": "https://placehold.co/200x200/525252/FFF?text=Ryzen 9 7900",
    "series": "Ryzen",
    "generation": "7000 (Zen 4)",
    "cores": 12,
    "threads": 24,
    "usecase": "General purpose",
    "generation_label": "7000 (Zen 4)",
    "stock": 100
  },
  {
    "id": "cpu-194",
    "name": "Ryzen 7 7800X3D",
    "brand": "AMD",
    "price": 38000,
    "image": "https://placehold.co/200x200/525252/FFF?text=Ryzen 7 7800X3D",
    "series": "Ryzen",
    "generation": "7000 (Zen 4)",
    "cores": 8,
    "threads": 16,
    "usecase": "Gaming-first",
    "generation_label": "7000 (Zen 4)",
    "stock": 100
  },
  {
    "id": "cpu-195",
    "name": "Ryzen 7 7700X",
    "brand": "AMD",
    "price": 35000,
    "image": "https://placehold.co/200x200/525252/FFF?text=Ryzen 7 7700X",
    "series": "Ryzen",
    "generation": "7000 (Zen 4)",
    "cores": 8,
    "threads": 16,
    "usecase": "General purpose",
    "generation_label": "7000 (Zen 4)",
    "stock": 100
  },
  {
    "id": "cpu-196",
    "name": "Ryzen 7 7700",
    "brand": "AMD",
    "price": 30000,
    "image": "https://placehold.co/200x200/525252/FFF?text=Ryzen 7 7700",
    "series": "Ryzen",
    "generation": "7000 (Zen 4)",
    "cores": 8,
    "threads": 16,
    "usecase": "Gaming + content creation",
    "generation_label": "7000 (Zen 4)",
    "stock": 100
  },
  {
    "id": "cpu-197",
    "name": "Ryzen 5 7600X",
    "brand": "AMD",
    "price": 22000,
    "image": "https://placehold.co/200x200/525252/FFF?text=Ryzen 5 7600X",
    "series": "Ryzen",
    "generation": "7000 (Zen 4)",
    "cores": 6,
    "threads": 12,
    "usecase": "All-round (gaming + dev + creator lite)",
    "generation_label": "7000 (Zen 4)",
    "stock": 100
  },
  {
    "id": "cpu-198",
    "name": "Ryzen 5 7600",
    "brand": "AMD",
    "price": 22000,
    "image": "https://placehold.co/200x200/525252/FFF?text=Ryzen 5 7600",
    "series": "Ryzen",
    "generation": "7000 (Zen 4)",
    "cores": 6,
    "threads": 12,
    "usecase": "Budget build / office / dev",
    "generation_label": "7000 (Zen 4)",
    "stock": 100
  },
  {
    "id": "cpu-199",
    "name": "Ryzen 5 7500F",
    "brand": "AMD",
    "price": 22000,
    "image": "https://placehold.co/200x200/525252/FFF?text=Ryzen 5 7500F",
    "series": "Ryzen",
    "generation": "7000 (Zen 4)",
    "cores": 6,
    "threads": 12,
    "usecase": "Budget build / office / dev",
    "generation_label": "7000 (Zen 4)",
    "stock": 100
  },
  {
    "id": "cpu-200",
    "name": "Ryzen 7 8700G",
    "brand": "AMD",
    "price": 35000,
    "image": "https://placehold.co/200x200/525252/FFF?text=Ryzen 7 8700G",
    "series": "Ryzen",
    "generation": "8000G (Zen 4 APU)",
    "cores": 8,
    "threads": 16,
    "usecase": "iGPU-only build / SFF",
    "generation_label": "8000G (Zen 4 APU)",
    "stock": 100
  },
  {
    "id": "cpu-201",
    "name": "Ryzen 5 8600G",
    "brand": "AMD",
    "price": 22000,
    "image": "https://placehold.co/200x200/525252/FFF?text=Ryzen 5 8600G",
    "series": "Ryzen",
    "generation": "8000G (Zen 4 APU)",
    "cores": 6,
    "threads": 12,
    "usecase": "All-round (gaming + dev + creator lite)",
    "generation_label": "8000G (Zen 4 APU)",
    "stock": 100
  },
  {
    "id": "cpu-202",
    "name": "Ryzen 5 8500G",
    "brand": "AMD",
    "price": 22000,
    "image": "https://placehold.co/200x200/525252/FFF?text=Ryzen 5 8500G",
    "series": "Ryzen",
    "generation": "8000G (Zen 4 APU)",
    "cores": 6,
    "threads": 12,
    "usecase": "Budget build / office / dev",
    "generation_label": "8000G (Zen 4 APU)",
    "stock": 100
  },
  {
    "id": "cpu-203",
    "name": "Ryzen 3 8300G",
    "brand": "AMD",
    "price": 14000,
    "image": "https://placehold.co/200x200/525252/FFF?text=Ryzen 3 8300G",
    "series": "Ryzen",
    "generation": "8000G (Zen 4 APU)",
    "cores": 4,
    "threads": 8,
    "usecase": "Budget build / office / dev",
    "generation_label": "8000G (Zen 4 APU)",
    "stock": 100
  }
]